utagmsengine/__init__.py
utagmsengine/dataclasses.py
utagmsengine/parser.py
utagmsengine/solver.py
utagmsengine/utils/__init__.py
utagmsengine/utils/dataclasses_utils.py
utagmsengine/utils/parser_utils.py
utagmsengine/utils/solver_utils.py
uta_gms_engine-0.0.30.dist-info/METADATA
uta_gms_engine-0.0.30.dist-info/WHEEL
uta_gms_engine-0.0.30.dist-info/top_level.txt
uta_gms_engine-0.0.30.dist-info/RECORD
